deck.py
deck-3.0.0.dist-info/WHEEL
deck-3.0.0.dist-info/METADATA
deck-3.0.0.dist-info/RECORD
