Metadata-Version: 2.1
Name: deck
Version: 3.0.0
Summary: Implementation of the deck collection type.
Home-page: http://github.com/zooba/deck
Author: Steve Dower
Author-email: steve.dower@python.org
Requires-Python: >=3.7
Classifier: Development Status :: 4 - Beta
Classifier: License :: Public Domain
Classifier: Programming Language :: Python :: 3.7
Classifier: Programming Language :: Python :: 3.8
Classifier: Programming Language :: Python :: 3.9
Classifier: Programming Language :: Python :: 3.10
